{
  "gpa": "0.00",
  "status": "DROPOUT",
  "subjects": [
    "gpa7: ref",
    "gpa6: ref",
    "gpa5: 2.75",
    "Unknown Subject (gpa4: 188438 { gpa7: ref)",
    "gpa6: ref",
    "gpa5: ref",
    "gpa4: ref",
    "Unknown Subject (188439 { gpa7: ref)",
    "gpa6: 2.75",
    "gpa5: ref",
    "Unknown Subject (gpa4: 188449 { gpa7: 2.55)",
    "gpa6: ref",
    "gpa5: ref",
    "gpa4:\n2.89",
    "gpa3: 2.79",
    "gpa2: 2.75",
    "gpa1: 3.05",
    "ref_sub: gpa3: ref",
    "gpa2: 3.00",
    "gpa1: 3.05",
    "ref_sub: 2.74",
    "gpa3: 2.96",
    "gpa2: 2.69",
    "gpa1: 3.25",
    "ref_sub: ref",
    "gpa3: 2.38",
    "gpa2: 2.32",
    "gpa1: 2.63",
    "Design of Structure-I (ref_sub:\n26464(T))",
    "Design of Structure-II (26474(T))",
    "Estimating & Costing-II (26475(T))"
  ],
  "held_in": "July-August, 2025",
  "regulation": "2022 Probidhan",
  "semester": "7th Semester"
}