{
  "gpa": "0.00",
  "status": "DROPOUT",
  "subjects": [
    "gpa7: ref",
    "gpa6: 2.68",
    "gpa5: 2.68",
    "Unknown Subject (gpa4: 189172 { gpa7: ref)",
    "gpa6: 2.75",
    "gpa5: 2.81",
    "Unknown Subject (gpa4: 189179 { gpa7: ref)",
    "gpa6: ref",
    "gpa5: 2.73",
    "Unknown Subject (gpa4: 189180 { gpa7: ref)",
    "gpa6: ref",
    "gpa5: 2.45",
    "gpa4:\n2.67",
    "gpa3: 2.52",
    "gpa2: 2.50",
    "gpa1: 2.35",
    "ref_sub: 2.67",
    "gpa3: 2.50",
    "gpa2: 2.44",
    "gpa1: 2.40",
    "ref_sub: 2.68",
    "gpa3: 2.73",
    "gpa2: 2.57",
    "gpa1: 2.38",
    "ref_sub: 2.85",
    "gpa3: 2.92",
    "gpa2: 2.46",
    "gpa1: 2.88",
    "Design of Structure-II (ref_sub:\n26474(T))"
  ],
  "held_in": "July-August, 2025",
  "regulation": "2022 Probidhan",
  "semester": "7th Semester"
}