{
  "gpa": "0.00",
  "status": "DROPOUT",
  "subjects": [
    "gpa7: ref",
    "gpa6: 3.70",
    "gpa5: 3.35",
    "Unknown Subject (gpa4: 602557 { gpa7: ref)",
    "gpa6: ref",
    "gpa5: 2.94",
    "Unknown Subject (gpa4: 602559 { gpa7: ref)",
    "gpa6: 3.77",
    "gpa5: 3.57",
    "Unknown Subject (gpa4: 602565 { gpa7: ref)",
    "gpa6: 3.37",
    "gpa5: ref",
    "gpa4:\n3.67",
    "gpa3: 3.49",
    "gpa2: 3.43",
    "gpa1: 3.86",
    "ref_sub: 2.27",
    "gpa3: 2.54",
    "gpa2: 2.83",
    "gpa1: 3.14",
    "ref_sub: 3.48",
    "gpa3: 2.98",
    "gpa2: 3.17",
    "gpa1: 3.55",
    "ref_sub: 2.79",
    "gpa3: 2.85",
    "gpa2: 2.95",
    "gpa1: 3.26",
    "Unknown Subject (ref_sub:\n25851(T))",
    "Unknown Subject (27071(T))"
  ],
  "held_in": "July-August, 2025",
  "regulation": "2022 Probidhan",
  "semester": "7th Semester"
}