{
  "gpa": "0.00",
  "status": "DROPOUT",
  "subjects": [
    "gpa7: 3.24",
    "gpa6: ref",
    "gpa5: 3.02",
    "Unknown Subject (gpa4: 607196 { gpa7: ref)",
    "gpa6: ref",
    "gpa5: 2.86",
    "Unknown Subject (gpa4: 607201 { gpa7: ref)",
    "gpa6: ref",
    "gpa5: 3.07",
    "Unknown Subject (gpa4: 607203 { gpa7: ref)",
    "gpa6: 3.04",
    "gpa5: 3.30",
    "gpa4:\n3.01",
    "gpa3: 3.14",
    "gpa2: 3.21",
    "gpa1: 3.39",
    "ref_sub: 2.95",
    "gpa3: 2.75",
    "gpa2: 2.98",
    "gpa1: 3.21",
    "ref_sub: ref",
    "gpa3: 2.86",
    "gpa2: 3.17",
    "gpa1: 3.64",
    "ref_sub: 3.10",
    "gpa3: 2.92",
    "gpa2: 3.31",
    "gpa1: 3.71",
    "Strength of Materials (ref_sub:\n27061(T))"
  ],
  "held_in": "July-August, 2025",
  "regulation": "2022 Probidhan",
  "semester": "7th Semester"
}