{
  "gpa": "0.00",
  "status": "DROPOUT",
  "subjects": [
    "gpa5: ref",
    "gpa4: 2.89",
    "gpa3: 2.48",
    "Unknown Subject (gpa2: 611397 { gpa5: 2.20)",
    "gpa4: 2.19",
    "gpa3: ref",
    "Unknown Subject (gpa2: 611411 { gpa5: ref)",
    "gpa4: ref",
    "gpa3: 2.55",
    "Unknown Subject (gpa2: 611417 { gpa5: ref)",
    "gpa4: ref",
    "gpa3: ref",
    "gpa2: ref",
    "2.84",
    "gpa1: 2.97",
    "Foundation Engineering (ref_sub: 26451(T))",
    "Surveying-III (26453(T))",
    "2.42",
    "gpa1: ref",
    "Mathematics -I (ref_sub: 25911(T))",
    "Mathematics-III (25931(T))"
  ],
  "held_in": "July-August, 2025",
  "regulation": "2022 Probidhan",
  "semester": "5th Semester"
}