{
  "gpa": "0.00",
  "status": "DROPOUT",
  "subjects": [
    "gpa7: ref",
    "gpa6: ref",
    "gpa5: ref",
    "gpa4: ref",
    "Unknown Subject (621581 { gpa7: ref)",
    "gpa6: ref",
    "gpa5: ref",
    "Unknown Subject (gpa4: 621583 { gpa7: ref)",
    "gpa6: 3.08",
    "gpa5: 3.20",
    "Unknown Subject (gpa4: 621589 { gpa7: ref)",
    "gpa6: ref",
    "gpa5: ref",
    "gpa4: ref",
    "gpa3: ref",
    "gpa2: 3.11",
    "gpa1: 3.36",
    "ref_sub: 3.01",
    "gpa3: 2.91",
    "gpa2: ref",
    "gpa1: ref",
    "ref_sub: 3.18",
    "gpa3: 3.47",
    "gpa2: 3.62",
    "gpa1: 3.95",
    "ref_sub: gpa3: 2.71",
    "gpa2: 3.06",
    "gpa1: ref",
    "Innovation & Entrepreneurship (ref_sub:\n25853(T))",
    "Mathematics-III (25931(T))",
    "Industrial Electronics (26833(T))",
    "Digital Electronics (26845(T))",
    "Physics -I (25912(T))",
    "Mathematics-II (25921(T))",
    "Industrial Electronics (26833(T))",
    "Digital Electronics (26845(T))",
    "Design of Machine Elements (27071(T))"
  ],
  "held_in": "July-August, 2025",
  "regulation": "2022 Probidhan",
  "semester": "7th Semester"
}