{
  "gpa": "0.00",
  "status": "DROPOUT",
  "subjects": [
    "gpa7: ref",
    "gpa6: 3.24",
    "gpa5: 3.21",
    "Unknown Subject (gpa4: 622678 { gpa7: ref)",
    "gpa6: 3.50",
    "gpa5: 3.26",
    "Unknown Subject (gpa4: 622681 { gpa7: ref)",
    "gpa6: 3.36",
    "gpa5: 3.05",
    "Unknown Subject (gpa4: 622685 { gpa7: ref)",
    "gpa6: 3.29",
    "gpa5: 3.26",
    "gpa4:\n3.24",
    "gpa3: ref",
    "gpa2: 2.97",
    "gpa1: 2.93",
    "ref_sub: 3.30",
    "gpa3: 3.24",
    "gpa2: 3.33",
    "gpa1: 3.57",
    "ref_sub: 2.71",
    "gpa3: 3.17",
    "gpa2: 3.28",
    "gpa1: 3.54",
    "ref_sub: 2.89",
    "gpa3: 3.13",
    "gpa2: 3.15",
    "gpa1: 3.39",
    "Chemistry (ref_sub:\n25913(T))",
    "Switch Gear and Protection (26773(T))"
  ],
  "held_in": "July-August, 2025",
  "regulation": "2022 Probidhan",
  "semester": "7th Semester"
}