{
  "gpa": "0.00",
  "status": "DROPOUT",
  "subjects": [
    "gpa7: ref",
    "gpa6: ref",
    "gpa5: 2.99",
    "Unknown Subject (gpa4: 623695 { gpa7: ref)",
    "gpa6: ref",
    "gpa5: 2.79",
    "Unknown Subject (gpa4: 623697 { gpa7: ref)",
    "gpa6: ref",
    "gpa5: 3.04",
    "Unknown Subject (gpa4: 623700 { gpa7: ref)",
    "gpa6: ref",
    "gpa5: 2.78",
    "gpa4:\n3.25",
    "gpa3: 2.77",
    "gpa2: 3.19",
    "gpa1: 3.31",
    "ref_sub: ref",
    "gpa3: ref",
    "gpa2: 2.70",
    "gpa1: 3.26",
    "ref_sub: 3.20",
    "gpa3: 2.63",
    "gpa2: 3.07",
    "gpa1: 3.76",
    "ref_sub: 2.85",
    "gpa3: 2.62",
    "gpa2: 2.78",
    "gpa1: 2.90",
    "AC Machine-I (ref_sub:\n26761(T))",
    "AC Machine-II (26771(T))",
    "Communication Engineering (26842(T))",
    "Progamming in C (28567(T))"
  ],
  "held_in": "July-August, 2025",
  "regulation": "2022 Probidhan",
  "semester": "7th Semester"
}