{
  "gpa": "0.00",
  "status": "DROPOUT",
  "subjects": [
    "gpa7: ref",
    "gpa6: ref",
    "gpa5: 2.44",
    "Unknown Subject (gpa4: 626190 { gpa7: ref)",
    "gpa6: 2.57",
    "gpa5: 2.25",
    "Unknown Subject (gpa4: 626195 { gpa7: ref)",
    "gpa6: 2.82",
    "gpa5: 2.83",
    "Unknown Subject (gpa4: 626199 { gpa7: ref)",
    "gpa6: ref",
    "gpa5: 2.24",
    "gpa4:\n2.40",
    "gpa3: 2.52",
    "gpa2: 2.49",
    "gpa1: 3.24",
    "ref_sub: 2.61",
    "gpa3: 2.81",
    "gpa2: 3.00",
    "gpa1: 2.95",
    "ref_sub: 2.88",
    "gpa3: 2.68",
    "gpa2: 2.79",
    "gpa1: 3.17",
    "ref_sub: 2.32",
    "gpa3: 2.35",
    "gpa2: 2.56",
    "gpa1: 2.88",
    "Hydraulics (ref_sub:\n26456(T))",
    "Design of Structure-II (26474(T))"
  ],
  "held_in": "July-August, 2025",
  "regulation": "2022 Probidhan",
  "semester": "7th Semester"
}