{
  "gpa": "0.00",
  "status": "DROPOUT",
  "subjects": [
    "gpa7: ref",
    "gpa6: 2.43",
    "gpa5: 2.56",
    "Unknown Subject (gpa4: 634371 { gpa7: ref)",
    "gpa6: ref",
    "gpa5: 2.29",
    "Unknown Subject (gpa4: 635294 { gpa7: ref)",
    "gpa6: 3.04",
    "gpa5: 2.76",
    "Unknown Subject (gpa4: 636305 { gpa7: ref)",
    "gpa6: 3.21",
    "gpa5: 2.74",
    "gpa4:\n2.61",
    "gpa3: 2.45",
    "gpa2: 2.74",
    "gpa1: 3.50",
    "ref_sub: ref",
    "gpa3: 2.57",
    "gpa2: 2.76",
    "gpa1: 3.74",
    "ref_sub: 2.96",
    "gpa3: 2.93",
    "gpa2: 3.34",
    "gpa1: 3.96",
    "ref_sub: 3.18",
    "gpa3: 2.73",
    "gpa2: 3.65",
    "gpa1: 3.98",
    "Design of Structure-II (ref_sub:\n26474(T))"
  ],
  "held_in": "July-August, 2025",
  "regulation": "2022 Probidhan",
  "semester": "7th Semester"
}