{
  "gpa": "0.00",
  "status": "DROPOUT",
  "subjects": [
    "Principles of Marketing (25851(T))",
    "Industrial Management (25852(T))",
    "Electrical Installation,Planning and Estimating (26741(T))",
    "Unknown Subject (630827 { 27051(T))",
    "Foundry & Pattern Making (27054(T))",
    "Manufacturing Process (27055(T))",
    "Unknown Subject (630834 { 25852(T))",
    "Fluid Mechanics & Machineries (27051(T))",
    "Foundry & Pattern Making (27054(T))",
    "Unknown Subject (730780 { 25852(T))",
    "Estimating & Costing-I (26442(T))",
    "Geotechnical Engineering (26445(T))",
    "Generation of Electrical Power (26751(T)",
    "P)",
    "Electrical & Electronic Measurements-I (26752(T)",
    "P)",
    "Testing and Maintannance of Electrical Equipments (26753(T)",
    "P)",
    "Electrical Engineering Project-II (26754(P))",
    "Progamming in C (28567(T))"
  ],
  "held_in": "July-August, 2025",
  "regulation": "2022 Probidhan",
  "semester": "5th Semester"
}