{
  "gpa": "0.00",
  "status": "DROPOUT",
  "subjects": [
    "gpa7: ref",
    "gpa6: ref",
    "gpa5: 3.10",
    "Unknown Subject (gpa4: 632880 { gpa7: ref)",
    "gpa6: 3.00",
    "gpa5: 3.16",
    "Unknown Subject (gpa4: 632883 { gpa7: ref)",
    "gpa6: ref",
    "gpa5: 2.90",
    "Unknown Subject (gpa4: 632886 { gpa7: ref)",
    "gpa6: ref",
    "gpa5: 3.08",
    "gpa4:\n3.15",
    "gpa3: 2.93",
    "gpa2: 3.09",
    "gpa1: 3.18",
    "ref_sub: 3.61",
    "gpa3: 3.13",
    "gpa2: 3.09",
    "gpa1: 3.43",
    "ref_sub: 3.26",
    "gpa3: 2.82",
    "gpa2: 2.95",
    "gpa1: 3.60",
    "ref_sub: 3.21",
    "gpa3: 2.82",
    "gpa2: 2.99",
    "gpa1: 3.27",
    "Innovation & Entrepreneurship (ref_sub:\n25853(T))",
    "Electrical & Electronic Measurements-II (26763(T))",
    "AC Machine-II (26771(T))",
    "Transmission and Distribution ofEllectrical Power-II (26772(T))"
  ],
  "held_in": "July-August, 2025",
  "regulation": "2022 Probidhan",
  "semester": "7th Semester"
}