{
  "gpa": "0.00",
  "status": "DROPOUT",
  "subjects": [
    "gpa7: ref",
    "gpa6: 2.40",
    "gpa5: 2.69",
    "Unknown Subject (gpa4: 636691 { gpa7: ref)",
    "gpa6: 2.56",
    "gpa5: 2.71",
    "Unknown Subject (gpa4: 636697 { gpa7: ref)",
    "gpa6: 2.54",
    "gpa5: 2.78",
    "Unknown Subject (gpa4: 636705 { gpa7: ref)",
    "gpa6: 2.43",
    "gpa5: ref",
    "gpa4:\n2.70",
    "gpa3: 2.74",
    "gpa2: ref",
    "gpa1: 3.67",
    "ref_sub: 3.02",
    "gpa3: 2.71",
    "gpa2: 2.58",
    "gpa1: 2.83",
    "ref_sub: 2.93",
    "gpa3: 3.02",
    "gpa2: 3.34",
    "gpa1: 3.21",
    "ref_sub: 2.98",
    "gpa3: 2.65",
    "gpa2: 2.70",
    "gpa1: 3.43",
    "Innovation & Entrepreneurship (ref_sub:\n25853(T))",
    "Mathematics-II (25921(T))",
    "Electrical Circuits-I (26721(T))",
    "Transmission and Distribution ofEllectrical Power-II (26772(T))"
  ],
  "held_in": "July-August, 2025",
  "regulation": "2022 Probidhan",
  "semester": "7th Semester"
}