{
  "gpa": "0.00",
  "status": "DROPOUT",
  "subjects": [
    "gpa7: ref",
    "gpa6: 3.18",
    "gpa5: 2.93",
    "Unknown Subject (gpa4: 639120 { gpa7: ref)",
    "gpa6: 3.18",
    "gpa5: 2.96",
    "Unknown Subject (gpa4: 639124 { gpa7: ref)",
    "gpa6: 3.23",
    "gpa5: 3.11",
    "Unknown Subject (gpa4: 639125 { gpa7: ref)",
    "gpa6: 3.54",
    "gpa5: 3.20",
    "gpa4:\n2.86",
    "gpa3: 2.81",
    "gpa2: 2.81",
    "gpa1: 2.75",
    "ref_sub: 2.90",
    "gpa3: 3.07",
    "gpa2: 3.02",
    "gpa1: 2.98",
    "ref_sub: 3.10",
    "gpa3: 3.06",
    "gpa2: 2.70",
    "gpa1: 2.98",
    "ref_sub: 3.17",
    "gpa3: 3.31",
    "gpa2: 2.76",
    "gpa1: 2.98",
    "Apps Development Project (ref_sub:\n28574(T))"
  ],
  "held_in": "July-August, 2025",
  "regulation": "2022 Probidhan",
  "semester": "7th Semester"
}