{
  "gpa": "0.00",
  "status": "DROPOUT",
  "subjects": [
    "gpa5: 2.68",
    "gpa4: 2.70",
    "gpa3: 2.95",
    "Unknown Subject (640234 { gpa5: ref)",
    "gpa4: 2.70",
    "gpa3: 2.63",
    "Unknown Subject (gpa2: 640238 { gpa5: ref)",
    "gpa4: ref",
    "gpa3: ref",
    "gpa2: ref",
    "Unknown Subject (640244 { gpa5: ref)",
    "gpa4: ref",
    "gpa3: ref",
    "gpa2:\ngpa2: ref",
    "gpa1: 3.10",
    "Electronic Devices and Circuits (ref_sub: 26821(T))"
  ],
  "held_in": "July-August, 2025",
  "regulation": "2022 Probidhan",
  "semester": "5th Semester"
}