{
  "gpa": "0.00",
  "status": "DROPOUT",
  "subjects": [
    "gpa7: ref",
    "gpa6: 2.89",
    "gpa5: 2.69",
    "Unknown Subject (gpa4: 642315 { gpa7: 2.55)",
    "gpa6: ref",
    "gpa5: 2.43",
    "Unknown Subject (gpa4: 642316 { gpa7: ref)",
    "gpa6: ref",
    "gpa5: ref",
    "gpa4: ref",
    "Unknown Subject (642321 { gpa7: ref)",
    "gpa6: 2.89",
    "gpa5: 3.13",
    "gpa4:\n2.87",
    "gpa3: 2.54",
    "gpa2: 2.96",
    "gpa1: 3.48",
    "ref_sub: 2.44",
    "gpa3: 2.39",
    "gpa2: 2.55",
    "gpa1: 2.86",
    "ref_sub: gpa3: ref",
    "gpa2: 2.80",
    "gpa1: 2.70",
    "ref_sub: 3.11",
    "gpa3: 2.81",
    "gpa2: 3.14",
    "gpa1: 3.18",
    "Design of Structure-II (ref_sub:\n26474(T))"
  ],
  "held_in": "July-August, 2025",
  "regulation": "2022 Probidhan",
  "semester": "7th Semester"
}