{
  "gpa": "0.00",
  "status": "DROPOUT",
  "subjects": [
    "gpa7: ref",
    "gpa6: 3.06",
    "gpa5: 3.26",
    "Unknown Subject (gpa4: 643133 { gpa7: ref)",
    "gpa6: 2.96",
    "gpa5: 3.34",
    "Unknown Subject (gpa4: 643142 { gpa7: ref)",
    "gpa6: 2.76",
    "gpa5: 3.01",
    "Unknown Subject (gpa4: 643181 { gpa7: ref)",
    "gpa6: 2.83",
    "gpa5: 3.19",
    "gpa4:\n2.44",
    "gpa3: 2.96",
    "gpa2: 3.13",
    "gpa1: 3.57",
    "ref_sub: 3.11",
    "gpa3: 3.18",
    "gpa2: 3.28",
    "gpa1: 3.71",
    "ref_sub: 2.68",
    "gpa3: 2.90",
    "gpa2: 2.91",
    "gpa1: 2.93",
    "ref_sub: 2.43",
    "gpa3: 2.70",
    "gpa2: 2.74",
    "gpa1: 2.85",
    "AC Machine-II (ref_sub:\n26771(T))",
    "Industrial Automation and PLC (26872(T))"
  ],
  "held_in": "July-August, 2025",
  "regulation": "2022 Probidhan",
  "semester": "7th Semester"
}