{
  "gpa": "0.00",
  "status": "DROPOUT",
  "subjects": [
    "gpa5: ref",
    "gpa4: ref",
    "gpa3: ref",
    "Unknown Subject (gpa2: 648143 { gpa5: ref)",
    "gpa4: ref",
    "gpa3: 2.64",
    "Unknown Subject (gpa2: 648366 { gpa5: ref)",
    "gpa4: 2.25",
    "gpa3: 2.25",
    "Unknown Subject (gpa2: 730994 { gpa5: ref)",
    "gpa4: 3.13",
    "gpa3: 3.18",
    "gpa2:\n2.60",
    "gpa1: 2.96",
    "Accounting (ref_sub: 25841(T))",
    "Basic Electronics (26811(T))",
    "ref",
    "gpa1: 2.91",
    "Basic Electricity (ref_sub: 26711(T))",
    "Engineering Mechanics (27041(T))",
    "ref",
    "gpa1: ref",
    "Accounting (ref_sub: 25841(T))",
    "Basic Electricity (26711(T))",
    "3.33",
    "gpa1: 3.41",
    "Civil CAD-II (ref_sub: 26452(T))",
    "Theory of Structure (26454(T))"
  ],
  "held_in": "July-August, 2025",
  "regulation": "2022 Probidhan",
  "semester": "5th Semester"
}