{
  "gpa": "0.00",
  "status": "DROPOUT",
  "subjects": [
    "gpa7: ref",
    "gpa6: 3.04",
    "gpa5: 2.85",
    "Unknown Subject (gpa4: 651419 { gpa7: ref)",
    "gpa6: 3.01",
    "gpa5: 3.24",
    "Unknown Subject (gpa4: 651420 { gpa7: ref)",
    "gpa6: ref",
    "gpa5: 2.80",
    "Unknown Subject (gpa4: 677855 { gpa7: ref)",
    "gpa6: 3.20",
    "gpa5: 3.03",
    "gpa4:\n2.49",
    "gpa3: 2.98",
    "gpa2: 2.57",
    "gpa1: 2.83",
    "ref_sub: 2.83",
    "gpa3: 2.98",
    "gpa2: 3.10",
    "gpa1: 3.38",
    "ref_sub: 2.50",
    "gpa3: 2.75",
    "gpa2: 2.56",
    "gpa1: 2.81",
    "ref_sub: 2.67",
    "gpa3: 3.02",
    "gpa2: 3.06",
    "gpa1: 3.40",
    "Advance Biomedical Equiment (ref_sub:\n28671(T))"
  ],
  "held_in": "July-August, 2025",
  "regulation": "2022 Probidhan",
  "semester": "7th Semester"
}