{
  "gpa": "0.00",
  "status": "DROPOUT",
  "subjects": [
    "gpa7: ref",
    "gpa6: 3.19",
    "gpa5: 2.91",
    "Unknown Subject (gpa4: 652828 { gpa7: ref)",
    "gpa6: 3.08",
    "gpa5: 2.84",
    "Unknown Subject (gpa4: 652829 { gpa7: ref)",
    "gpa6: 2.61",
    "gpa5: 3.04",
    "Unknown Subject (gpa4: 652833 { gpa7: ref)",
    "gpa6: 3.39",
    "gpa5: 3.23",
    "gpa4:\n2.54",
    "gpa3: 2.40",
    "gpa2: 2.64",
    "gpa1: 3.35",
    "ref_sub: 2.83",
    "gpa3: 2.70",
    "gpa2: 2.62",
    "gpa1: 3.15",
    "ref_sub: 3.07",
    "gpa3: 2.71",
    "gpa2: 2.67",
    "gpa1: 3.08",
    "ref_sub: 3.29",
    "gpa3: 2.74",
    "gpa2: 2.71",
    "gpa1: 3.38",
    "Innovation & Entrepreneurship (ref_sub:\n25853(T))"
  ],
  "held_in": "July-August, 2025",
  "regulation": "2022 Probidhan",
  "semester": "7th Semester"
}