{
  "gpa": "0.00",
  "status": "DROPOUT",
  "subjects": [
    "gpa7: ref",
    "gpa6: 3.21",
    "gpa5: 2.96",
    "Unknown Subject (gpa4: 655502 { gpa7: ref)",
    "gpa6: 3.46",
    "gpa5: 3.55",
    "Unknown Subject (gpa4: 655503 { gpa7: 2.92)",
    "gpa6: ref",
    "gpa5: 2.85",
    "Unknown Subject (gpa4: 655504 { gpa7: ref)",
    "gpa6: ref",
    "gpa5: 2.96",
    "gpa4:\n3.36",
    "gpa3: 3.18",
    "gpa2: 3.26",
    "gpa1: 3.30",
    "ref_sub: 3.62",
    "gpa3: 3.43",
    "gpa2: 3.56",
    "gpa1: 3.76",
    "ref_sub: 3.27",
    "gpa3: ref",
    "gpa2: 3.40",
    "gpa1: 3.54",
    "ref_sub: 3.07",
    "gpa3: 2.87",
    "gpa2: 3.18",
    "gpa1: 3.20",
    "Design of Structure-II (ref_sub:\n26474(T))",
    "Construction Management & Documentation (28871(T))"
  ],
  "held_in": "July-August, 2025",
  "regulation": "2022 Probidhan",
  "semester": "7th Semester"
}