{
  "gpa": "0.00",
  "status": "DROPOUT",
  "subjects": [
    "gpa7: ref",
    "gpa6: 2.54",
    "gpa5: ref",
    "Unknown Subject (gpa4: 658386 { gpa7: ref)",
    "gpa6: ref",
    "gpa5: 2.27",
    "Unknown Subject (gpa4: 658409 { gpa7: ref)",
    "gpa6: ref",
    "gpa5: 2.40",
    "Business Origination & Communication (gpa4: 658410 { gpa7: ref)",
    "gpa6: ref",
    "gpa5: ref",
    "gpa4:\nref",
    "gpa3: 2.43",
    "gpa2: 2.44",
    "gpa1: 2.90",
    "ref_sub: 2.12",
    "gpa3: 2.70",
    "gpa2: 2.80",
    "gpa1: 2.90",
    "ref_sub: 2.31",
    "gpa3: 2.29",
    "gpa2: 2.63",
    "gpa1: 2.93",
    "ref_sub: 2.26",
    "gpa3: 2.39",
    "gpa2: 2.37",
    "gpa1: 2.98",
    "Engineering Mechanics (ref_sub:\n27041(T))",
    "Fluid Mechanics & Machineries (27051(T))",
    "Design of Machine Elements (27071(T))",
    "Service Station Operation & Estimating (27171(T))"
  ],
  "held_in": "July-August, 2025",
  "regulation": "2022 Probidhan",
  "semester": "7th Semester"
}