{
  "gpa": "0.00",
  "status": "DROPOUT",
  "subjects": [
    "gpa7: ref",
    "gpa6: ref",
    "gpa5: ref",
    "gpa4: ref",
    "Unknown Subject (660814 { gpa7: ref)",
    "gpa6: ref",
    "gpa5: ref",
    "Unknown Subject (gpa4: 660815 { gpa7: 3.51)",
    "gpa6: ref",
    "gpa5: ref",
    "Unknown Subject (gpa4: 660820 { gpa7: ref)",
    "gpa6: 3.29",
    "gpa5: 3.25",
    "gpa4:\ngpa3: ref",
    "gpa2: 3.06",
    "gpa1: 3.46",
    "ref_sub: 2.99",
    "gpa3: ref",
    "gpa2: ref",
    "gpa1: 2.95",
    "ref_sub: 3.19",
    "gpa3: 3.00",
    "gpa2: 3.16",
    "gpa1: 3.68",
    "ref_sub: 3.17",
    "gpa3: 2.86",
    "gpa2: 3.15",
    "gpa1: 3.62",
    "Mathematics-III (ref_sub:\n25931(T))",
    "Estimating & Costing-I (26442(T))",
    "Theory of Structure (26454(T))",
    "Hydraulics (26456(T))",
    "Mathematics-II (25921(T))",
    "Physics-II (25922(T))",
    "Theory of Structure (26454(T))",
    "Hydraulics (26456(T))",
    "Water Supply Engineering (26455(T))",
    "Hydraulics (26456(T))",
    "Design of Structure-I (26464(T))"
  ],
  "held_in": "July-August, 2025",
  "regulation": "2022 Probidhan",
  "semester": "7th Semester"
}