{
  "gpa": "0.00",
  "status": "DROPOUT",
  "subjects": [
    "gpa7: ref",
    "gpa6: 3.36",
    "gpa5: 3.50",
    "Unknown Subject (gpa4: 665508 { gpa7: ref)",
    "gpa6: 3.41",
    "gpa5: 3.63",
    "Unknown Subject (gpa4: 665513 { gpa7: ref)",
    "gpa6: 3.63",
    "gpa5: 3.58",
    "Unknown Subject (gpa4: 665515 { gpa7: ref)",
    "gpa6: 3.24",
    "gpa5: 3.35",
    "gpa4:\n3.37",
    "gpa3: 3.54",
    "gpa2: 3.50",
    "gpa1: 3.75",
    "ref_sub: 3.13",
    "gpa3: 3.40",
    "gpa2: 3.32",
    "gpa1: 3.25",
    "ref_sub: 3.30",
    "gpa3: 3.54",
    "gpa2: 3.60",
    "gpa1: 3.78",
    "ref_sub: 3.04",
    "gpa3: 3.40",
    "gpa2: 3.19",
    "gpa1: 3.60",
    "Cyber Security & Ethics (ref_sub:\n28573(T))"
  ],
  "held_in": "July-August, 2025",
  "regulation": "2022 Probidhan",
  "semester": "7th Semester"
}