{
  "gpa": "0.00",
  "status": "DROPOUT",
  "subjects": [
    "gpa7: 2.50",
    "gpa6: 2.21",
    "gpa5: 2.19",
    "Game Development (666792 { gpa7: ref)",
    "gpa6: 2.79",
    "gpa5: 2.63",
    "Game Development (gpa4: 666794 { gpa7: ref)",
    "gpa6: 2.93",
    "gpa5: 2.55",
    "gpa4:\ngpa4: 2.40",
    "gpa3: ref",
    "gpa2: 2.71",
    "gpa1: 2.75",
    "2.77",
    "gpa3: 2.38",
    "gpa2: 2.60",
    "gpa1: 3.36",
    "ref_sub: 3.24",
    "gpa3: 2.69",
    "gpa2: 3.30",
    "gpa1: 3.29",
    "Mathematics-III (ref_sub:\nref_sub: 25931(T))"
  ],
  "held_in": "July-August, 2025",
  "regulation": "2022 Probidhan",
  "semester": "7th Semester"
}