{
  "gpa": "0.00",
  "status": "DROPOUT",
  "subjects": [
    "gpa7: ref",
    "gpa6: 3.38",
    "gpa5: 3.14",
    "Advance Electricity (gpa4: 667325 { gpa7: ref)",
    "gpa6: 3.23",
    "gpa5: 3.46",
    "Electrical Engineering Drawing (gpa4: 667330 { gpa7: ref)",
    "gpa6: 3.38",
    "gpa5: 3.50",
    "Electrical Engineering Drawing (gpa4: 667333 { gpa7: ref)",
    "gpa6: 3.40",
    "gpa5: 2.98",
    "gpa4:\n3.37",
    "gpa3: 3.01",
    "gpa2: 3.26",
    "gpa1: 3.30",
    "ref_sub: 3.37",
    "gpa3: 3.05",
    "gpa2: 3.45",
    "gpa1: 3.45",
    "ref_sub: 3.38",
    "gpa3: 3.04",
    "gpa2: ref",
    "gpa1: 3.28",
    "ref_sub: 3.11",
    "gpa3: 3.00",
    "gpa2: 2.89",
    "gpa1: 3.43",
    "Cyber Security & Ethics (ref_sub:\n28573(T))"
  ],
  "held_in": "July-August, 2025",
  "regulation": "2022 Probidhan",
  "semester": "7th Semester"
}