{
  "gpa": "0.00",
  "status": "DROPOUT",
  "subjects": [
    "gpa7: ref",
    "gpa6: ref",
    "gpa5: 3.45",
    "Unknown Subject (gpa4: 667351 { gpa7: ref)",
    "gpa6: ref",
    "gpa5: 3.28",
    "Unknown Subject (gpa4: 667354 { gpa7: ref)",
    "gpa6: 3.48",
    "gpa5: 3.45",
    "Unknown Subject (gpa4: 667355 { gpa7: ref)",
    "gpa6: ref",
    "gpa5: ref",
    "gpa4:\n3.35",
    "gpa3: 3.48",
    "gpa2: 3.40",
    "gpa1: 3.60",
    "ref_sub: 3.17",
    "gpa3: 3.02",
    "gpa2: 3.24",
    "gpa1: 3.48",
    "ref_sub: 3.24",
    "gpa3: 3.26",
    "gpa2: 3.17",
    "gpa1: 3.57",
    "ref_sub: 3.10",
    "gpa3: ref",
    "gpa2: 3.17",
    "gpa1: 3.50",
    "Communication Engineering (ref_sub:\n26842(T))",
    "Automation Engineering & PLC (26875(T))"
  ],
  "held_in": "July-August, 2025",
  "regulation": "2022 Probidhan",
  "semester": "7th Semester"
}