{
  "gpa": "0.00",
  "status": "DROPOUT",
  "subjects": [
    "gpa7: 3.44",
    "gpa6: ref",
    "gpa5: 3.25",
    "Unknown Subject (gpa4: 667579 { gpa7: ref)",
    "gpa6: ref",
    "gpa5: 3.09",
    "Unknown Subject (gpa4: 667581 { gpa7: ref)",
    "gpa6: ref",
    "gpa5: 3.13",
    "Unknown Subject (gpa4: 667584 { gpa7: ref)",
    "gpa6: ref",
    "gpa5: 3.31",
    "gpa4:\n3.29",
    "gpa3: 2.88",
    "gpa2: ref",
    "gpa1: 3.26",
    "ref_sub: 3.13",
    "gpa3: 2.89",
    "gpa2: 3.13",
    "gpa1: 3.25",
    "ref_sub: 3.13",
    "gpa3: 2.94",
    "gpa2: ref",
    "gpa1: 3.12",
    "ref_sub: 3.08",
    "gpa3: 3.11",
    "gpa2: 2.84",
    "gpa1: 3.50",
    "Mathematics-II (ref_sub:\n25921(T))",
    "Strength of Materials (27061(T))"
  ],
  "held_in": "July-August, 2025",
  "regulation": "2022 Probidhan",
  "semester": "7th Semester"
}