{
  "gpa": "0.00",
  "status": "DROPOUT",
  "subjects": [
    "gpa7: ref",
    "gpa6: 2.94",
    "gpa5: 2.95",
    "Unknown Subject (gpa4: 669289 { gpa7: ref)",
    "gpa6: 2.89",
    "gpa5: 3.14",
    "Unknown Subject (gpa4: 669304 { gpa7: ref)",
    "gpa6: 3.30",
    "gpa5: 3.11",
    "Catering Management (gpa4: 669310 { gpa7: ref)",
    "gpa6: 3.28",
    "gpa5: ref",
    "gpa4:\nref",
    "gpa3: 2.82",
    "gpa2: 2.74",
    "gpa1: 2.93",
    "ref_sub: 2.74",
    "gpa3: 2.94",
    "gpa2: 3.11",
    "gpa1: 3.40",
    "ref_sub: ref",
    "gpa3: 2.86",
    "gpa2: 2.65",
    "gpa1: 3.08",
    "ref_sub: ref",
    "gpa3: 2.94",
    "gpa2: 2.91",
    "gpa1: 2.89",
    "Radio and TV Engineering (ref_sub:\n29441(T))",
    "Microwave Engineering and Antennas (29471(T))",
    "Optical Fiber Communication (29472(T))"
  ],
  "held_in": "July-August, 2025",
  "regulation": "2022 Probidhan",
  "semester": "7th Semester"
}