{
  "gpa": "0.00",
  "status": "DROPOUT",
  "subjects": [
    "gpa7: ref",
    "gpa6: 3.15",
    "gpa5: 2.90",
    "Glass House Refractory (gpa4: 677764 { gpa7: ref)",
    "gpa6: 2.48",
    "gpa5: 2.53",
    "Glass House Refractory (gpa4: 677765 { gpa7: ref)",
    "gpa6: 2.66",
    "gpa5: 2.41",
    "Glass House Refractory (gpa4: 677769 { gpa7: ref)",
    "gpa6: 2.55",
    "gpa5: 2.43",
    "gpa4:\n2.86",
    "gpa3: 2.83",
    "gpa2: 2.69",
    "gpa1: 3.10",
    "ref_sub: 2.82",
    "gpa3: 2.60",
    "gpa2: 2.51",
    "gpa1: 3.13",
    "ref_sub: 2.55",
    "gpa3: 2.52",
    "gpa2: 2.36",
    "gpa1: 2.85",
    "ref_sub: 2.75",
    "gpa3: 2.67",
    "gpa2: 2.57",
    "gpa1: 3.23",
    "Network Administration & Services (ref_sub:\n28572(T))"
  ],
  "held_in": "July-August, 2025",
  "regulation": "2022 Probidhan",
  "semester": "7th Semester"
}