{
  "gpa": "0.00",
  "status": "DROPOUT",
  "subjects": [
    "gpa7: ref",
    "gpa6: 3.09",
    "gpa5: 2.58",
    "Unknown Subject (gpa4: 688207 { gpa7: ref)",
    "gpa6: 2.60",
    "gpa5: 2.52",
    "Unknown Subject (gpa4: 688208 { gpa7: ref)",
    "gpa6: ref",
    "gpa5: 2.80",
    "Unknown Subject (gpa4: 688214 { gpa7: ref)",
    "gpa6: 2.41",
    "gpa5: 2.72",
    "gpa4:\n2.61",
    "gpa3: 2.80",
    "gpa2: 2.57",
    "gpa1: 2.95",
    "ref_sub: 2.95",
    "gpa3: 2.62",
    "gpa2: 2.52",
    "gpa1: 2.82",
    "ref_sub: 2.83",
    "gpa3: 2.71",
    "gpa2: ref",
    "gpa1: 2.73",
    "ref_sub: 2.81",
    "gpa3: 2.59",
    "gpa2: 2.40",
    "gpa1: 2.88",
    "Mechatronics & PLC (ref_sub:\n29231(T))"
  ],
  "held_in": "July-August, 2025",
  "regulation": "2022 Probidhan",
  "semester": "7th Semester"
}