{
  "gpa": "0.00",
  "status": "DROPOUT",
  "subjects": [
    "gpa5: ref",
    "gpa4: 3.43",
    "gpa3: 3.48",
    "Unknown Subject (gpa2: 702016 { gpa5: ref)",
    "gpa4: ref",
    "gpa3: 3.26",
    "Unknown Subject (gpa2: 702017 { gpa5: ref)",
    "gpa4: ref",
    "gpa3: 3.10",
    "Unknown Subject (gpa2: 702021 { gpa5: ref)",
    "gpa4: 3.71",
    "gpa3: 3.67",
    "gpa2:\n3.50",
    "gpa1: 3.55",
    "Microprocessor & Microcontroller (ref_sub: 26853(T))"
  ],
  "held_in": "July-August, 2025",
  "regulation": "2022 Probidhan",
  "semester": "5th Semester"
}