{
  "gpa": "0.00",
  "status": "DROPOUT",
  "subjects": [
    "gpa5: ref",
    "gpa4: 3.15",
    "gpa3: 3.21",
    "Unknown Subject (gpa2: 705627 { gpa5: ref)",
    "gpa4: 3.24",
    "gpa3: 3.64",
    "Unknown Subject (gpa2: 705631 { gpa5: ref)",
    "gpa4: ref",
    "gpa3: ref",
    "Unknown Subject (gpa2: 705632 { gpa5: ref)",
    "gpa4: ref",
    "gpa3: 3.49",
    "gpa2:\n3.50",
    "gpa1: 3.15",
    "Industrial Management (ref_sub: 25852(T))",
    "Foundation Engineering (26451(T))",
    "3.28",
    "gpa1: 3.55",
    "Foundation Engineering (ref_sub: 26451(T))",
    "Water Supply Engineering (26455(T))",
    "3.38",
    "gpa1: 3.35",
    "Industrial Management (ref_sub: 25852(T))",
    "Surveying-I (26432(T))",
    "3.48",
    "gpa1: 3.43",
    "Industrial Management (ref_sub: 25852(T))",
    "Surveying-II (26444(T))",
    "Hydraulics (26456(T))"
  ],
  "held_in": "July-August, 2025",
  "regulation": "2022 Probidhan",
  "semester": "5th Semester"
}