{
  "gpa": "0.00",
  "status": "DROPOUT",
  "subjects": [
    "gpa5: ref",
    "gpa4: ref",
    "gpa3: ref",
    "gpa2: ref",
    "Unknown Subject (707627 { gpa5: ref)",
    "gpa4: 2.59",
    "gpa3: 2.50",
    "Unknown Subject (gpa2: 707630 { gpa5: ref)",
    "gpa4: 2.96",
    "gpa3: 3.17",
    "Unknown Subject (gpa2: 707632 { gpa5: ref)",
    "gpa4: 2.77",
    "gpa3: 3.04",
    "gpa2:\ngpa1: 2.88",
    "Mathematics-III (ref_sub: 25931(T))",
    "Electronic Devices and Circuits (26821(T))",
    "2.54",
    "gpa1: 2.96",
    "Bio-Medical Instruments (ref_sub: 28654(T))"
  ],
  "held_in": "July-August, 2025",
  "regulation": "2022 Probidhan",
  "semester": "5th Semester"
}