{
  "gpa": "0.00",
  "status": "DROPOUT",
  "subjects": [
    "gpa5: ref",
    "gpa4: ref",
    "gpa3: 2.69",
    "Unknown Subject (gpa2: 725656 { gpa5: ref)",
    "gpa4: ref",
    "gpa3: 2.68",
    "Unknown Subject (gpa2: 725660 { gpa5: 2.90)",
    "gpa4: ref",
    "gpa3: 2.56",
    "Unknown Subject (gpa2: 725667 { gpa5: ref)",
    "gpa4: 3.02",
    "gpa3: 2.99",
    "gpa2:\n2.74",
    "gpa1: 3.26",
    "Generation of Electrical Power (ref_sub: 26751(T))",
    "Electrical & Electronic Measurements-I (26752(T))",
    "2.67",
    "gpa1: 3.19",
    "Generation of Electrical Power (ref_sub: 26751(T))",
    "Electrical & Electronic Measurements-I (26752(T))",
    "2.64",
    "gpa1: 3.33",
    "Applied Mechanics (ref_sub: 27044(T))"
  ],
  "held_in": "July-August, 2025",
  "regulation": "2022 Probidhan",
  "semester": "5th Semester"
}