{
  "gpa": "0.00",
  "status": "DROPOUT",
  "subjects": [
    "gpa5: ref",
    "gpa4: ref",
    "gpa3: ref",
    "gpa2: ref",
    "Unknown Subject (742000 { gpa5: ref)",
    "gpa4: 3.17",
    "gpa3: ref",
    "Unknown Subject (gpa2: 742001 { gpa5: ref)",
    "gpa4: 3.32",
    "gpa3: ref",
    "Unknown Subject (gpa2: 742002 { gpa5: ref)",
    "gpa4: ref",
    "gpa3: 3.43",
    "gpa2:\ngpa1: ref",
    "Mathematics -I (ref_sub: 25911(T))",
    "Physics -I (25912(T))",
    "Chemistry (25913(T))",
    "3.13",
    "gpa1: 3.07",
    "Structural Mechanics (ref_sub: 26431(T))",
    "Theory of Structure (26454(T))",
    "3.30",
    "gpa1: 3.28",
    "Structural Mechanics (ref_sub: 26431(T))",
    "Civil CAD-II (26452(T))",
    "3.55",
    "gpa1: 3.17",
    "Surveying-II (ref_sub: 26444(T))",
    "Theory of Structure (26454(T))",
    "Mathematics-II (25921(T))",
    "Physics-II (25922(T))",
    "Mathematics-III (25931(T))",
    "Engineering Mechanics (27041(T))",
    "Hydraulics (26456(T))"
  ],
  "held_in": "July-August, 2025",
  "regulation": "2022 Probidhan",
  "semester": "5th Semester"
}