{
  "gpa": "0.00",
  "status": "DROPOUT",
  "subjects": [
    "gpa5: ref",
    "gpa4: ref",
    "gpa3: 2.70",
    "Unknown Subject (gpa2: 742826 { gpa5: ref)",
    "gpa4: 2.80",
    "gpa3: ref",
    "Unknown Subject (gpa2: 742827 { gpa5: ref)",
    "gpa4: ref",
    "gpa3: 2.87",
    "Unknown Subject (gpa2: 742830 { gpa5: ref)",
    "gpa4: 2.57",
    "gpa3: 2.62",
    "gpa2:\n2.95",
    "gpa1: 3.14",
    "Electrical Installation,Planning and Estimating (ref_sub: 26741(T))",
    "Generation of Electrical Power (26751(T))",
    "2.50",
    "gpa1: 2.83",
    "Industrial Electronics (ref_sub: 26833(T))",
    "Microprocessor & Microcontroller (26853(T))"
  ],
  "held_in": "July-August, 2025",
  "regulation": "2022 Probidhan",
  "semester": "5th Semester"
}