{
  "gpa": "0.00",
  "status": "DROPOUT",
  "subjects": [
    "gpa5: ref",
    "gpa4: 2.96",
    "gpa3: 2.93",
    "Unknown Subject (gpa2: 745048 { gpa5: ref)",
    "gpa4: ref",
    "gpa3: 2.74",
    "Unknown Subject (gpa2: 745049 { gpa5: ref)",
    "gpa4: ref",
    "gpa3: 3.11",
    "Unknown Subject (gpa2: 745060 { gpa5: ref)",
    "gpa4: ref",
    "gpa3: ref",
    "gpa2:\n2.72",
    "gpa1: 2.70",
    "Television Engineering (ref_sub: 26851(T))",
    "Progamming in C (28567(T))"
  ],
  "held_in": "July-August, 2025",
  "regulation": "2022 Probidhan",
  "semester": "5th Semester"
}