{
  "gpa": "0.00",
  "status": "DROPOUT",
  "subjects": [
    "Automobile Air- Conditioning (26251(T))",
    "Fluid Mechanics & Machineries (27051(T))",
    "Mechanical Estimating & Costing (27052(T))",
    "Unknown Subject (763761 { 25851(T))",
    "Industrial Management (25852(T))",
    "Electrical Circuits-I (26721(T))",
    "Unknown Subject (763778 { 25851(T))",
    "Industrial Management (25852(T))",
    "Generation of Electrical Power (26751(T)",
    "P)",
    "Unknown Subject (790242 { 26251(T))",
    "Basic Electronics (26811(T))",
    "Fluid Mechanics & Machineries (27051(T))",
    "Advanced Welding-I (27053(T))"
  ],
  "held_in": "July-August, 2025",
  "regulation": "2022 Probidhan",
  "semester": "5th Semester"
}