{
  "gpa": "0.00",
  "status": "DROPOUT",
  "subjects": [
    "Accounting (25841(T))",
    "Basic Electronics (26811(T))",
    "Machine Shop Practice-II (27032(T))",
    "Unknown Subject (773348 { 25831(T))",
    "Physics -I (25912(T))",
    "Basic Electricity (26711(T))",
    "Unknown Subject (773375 { 26841(T))",
    "Java Programming (28541(T))",
    "Computer Peripherals & Interfacing (28543(T))",
    "Engineering Mechanics (27041(T))",
    "Machine Shop Practice III (27042(T)",
    "P)",
    "Metallurgy2 (27043(T))",
    "RAC Cycles and Components (27231(T))",
    "Digital Electronics-II (26841(T))",
    "Application Development Using Python (28531(T))",
    "Java Programming (28541(T))",
    "Data Structure & Algorithm (28542(T))",
    "Web Design & Development-I (28544(T))"
  ],
  "held_in": "July-August, 2025",
  "regulation": "2022 Probidhan",
  "semester": "4th Semester"
}