{
  "gpa": "0.00",
  "status": "DROPOUT",
  "subjects": [
    "gpa5: 2.49",
    "gpa4: 3.15",
    "gpa3: ref",
    "Unknown Subject (gpa2: 776671 { gpa5: ref)",
    "gpa4: 3.18",
    "gpa3: 2.64",
    "Unknown Subject (gpa2: 776674 { gpa5: ref)",
    "gpa4: 2.85",
    "gpa3: 2.83",
    "Unknown Subject (gpa2: 776678 { gpa5: ref)",
    "gpa4: 3.18",
    "gpa3: 3.11",
    "gpa2:\n2.62",
    "gpa1: 3.10",
    "Mathematics-III (ref_sub: 25931(T))",
    "IT Support Services (28533(T))"
  ],
  "held_in": "July-August, 2025",
  "regulation": "2022 Probidhan",
  "semester": "5th Semester"
}