{
  "gpa": "0.00",
  "status": "DROPOUT",
  "subjects": [
    "gpa5: ref",
    "gpa4: 3.38",
    "gpa3: 3.48",
    "Unknown Subject (gpa2: 784410 { gpa5: ref)",
    "gpa4: 3.23",
    "gpa3: 2.95",
    "Unknown Subject (gpa2: 784413 { gpa5: ref)",
    "gpa4: 2.87",
    "gpa3: 3.04",
    "Unknown Subject (gpa2: 784430 { gpa5: ref)",
    "gpa4: 2.63",
    "gpa3: 2.85",
    "gpa2:\n3.39",
    "gpa1: 3.53",
    "Accounting (ref_sub: 25841(T))",
    "Computer Architecture & Microprocessor (28553(T))"
  ],
  "held_in": "July-August, 2025",
  "regulation": "2022 Probidhan",
  "semester": "5th Semester"
}