{
  "gpa": "0.00",
  "status": "DROPOUT",
  "subjects": [
    "gpa3: ref",
    "gpa2: 3.30",
    "gpa1: 3.67",
    "Unknown Subject (811353 { gpa3: ref)",
    "gpa2: ref",
    "gpa1: 3.08",
    "Unknown Subject (ref_sub: 811356 { gpa3: ref)",
    "gpa2: ref",
    "gpa1: 3.08",
    "Unknown Subject (ref_sub: 811358 { gpa3: ref)",
    "gpa2: ref",
    "gpa1: ref",
    "RAC Cycles and Components (ref_sub:\nref_sub: 27231(T))"
  ],
  "held_in": "July-August, 2025",
  "regulation": "2022 Probidhan",
  "semester": "3rd Semester"
}