{
  "gpa": "0.00",
  "status": "DROPOUT",
  "subjects": [
    "gpa3: ref",
    "gpa2: 3.08",
    "gpa1: 3.26",
    "Unknown Subject (834644 { gpa3: ref)",
    "gpa2: 2.93",
    "gpa1: 3.06",
    "Unknown Subject (834712 { gpa3: ref)",
    "gpa2: 2.59",
    "gpa1: 2.79",
    "Unknown Subject (834887 { gpa3: ref)",
    "gpa2: ref",
    "gpa1: 2.93",
    "Electrical Circuits-II (ref_sub:\nref_sub: 26731(T))",
    "Industrial Electronics (26833(T))"
  ],
  "held_in": "July-August, 2025",
  "regulation": "2022 Probidhan",
  "semester": "3rd Semester"
}