{
  "gpa": "0.00",
  "status": "DROPOUT",
  "subjects": [
    "Physics-II (25922(T)",
    "P)",
    "Mathematics-III (25931(P))",
    "Civil Engineering Metarials (26411(T)",
    "P)",
    "Unknown Subject (852557 { 25921(T))",
    "Physics-II (25922(T))",
    "Mathematics-III (25931(T))",
    "Unknown Subject (852559 { 25913(T))",
    "Mathematics-II (25921(T))",
    "Physics-II (25922(T)",
    "P)",
    "Unknown Subject (852561 { 25921(T))",
    "Physics-II (25922(T)",
    "P)",
    "Mathematics-III (25931(T)",
    "P)",
    "Surveying-I (26432(T)",
    "P)",
    "Construction Process-I (26433(P))",
    "Basic Electricity (26711(T))",
    "Basic Workshop Practice (27011(P))",
    "Civil Engineering Metarials (26411(T))",
    "Civil Engineering Drawing (26421(T))",
    "Surveying-I (26432(T))"
  ],
  "held_in": "July-August, 2025",
  "regulation": "2022 Probidhan",
  "semester": "3rd Semester"
}