{
  "gpa": "0.00",
  "status": "DROPOUT",
  "subjects": [
    "gpa3: ref",
    "gpa2: ref",
    "gpa1: 2.99",
    "Unknown Subject (ref_sub: 861237 { gpa3: ref)",
    "gpa2: ref",
    "gpa1: 3.08",
    "Unknown Subject (ref_sub: 861239 { gpa3: ref)",
    "gpa2: ref",
    "gpa1: 3.36",
    "Unknown Subject (ref_sub: 861242 { gpa3: ref)",
    "gpa2: ref",
    "gpa1: 3.24",
    "Business Communication (ref_sub:\n25831(T))",
    "Mathematics-II (25921(T))",
    "Physics-II (25922(T))",
    "Mathematics-III (25931(T))"
  ],
  "held_in": "July-August, 2025",
  "regulation": "2022 Probidhan",
  "semester": "3rd Semester"
}