{
  "gpa": "0.00",
  "status": "DROPOUT",
  "subjects": [
    "Social Science (25811(T))",
    "Mathematics -I (25911(T))",
    "Physics -I (25912(T))",
    "Unknown Subject (865593 { 25911(T))",
    "Chemistry (25913(T))",
    "Physics-II (25922(T))",
    "Unknown Subject (865607 { 25811(T))",
    "Mathematics -I (25911(T))",
    "Chemistry (25913(T))",
    "Unknown Subject (865611 { 25811(T))",
    "Physics-II (25922(T)",
    "P)",
    "Mathematics-III (25931(T)",
    "P)",
    "Physics-II (25922(T))",
    "Mathematics-III (25931(T))",
    "Basic Electronics (26811(T))",
    "Digital Electronics-I (26831(T))",
    "Mathematics-III (25931(T))",
    "Digital Electronics-I (26831(T))",
    "Python Programming (28521(T))",
    "Application Development Using Python (28531(T))"
  ],
  "held_in": "July-August, 2025",
  "regulation": "2022 Probidhan",
  "semester": "3rd Semester"
}